sqlformatter/__init__.py
sqlformatter/__main__.py
sqlformatter/cli.py
sqlformatter/config.py
sqlformatter/helpers.py
sqlformatter/sql_query.py
sqlformatter/sqlformatter.py
sqlmakeuper-0.1.4.dist-info/LICENSE
sqlmakeuper-0.1.4.dist-info/METADATA
sqlmakeuper-0.1.4.dist-info/WHEEL
sqlmakeuper-0.1.4.dist-info/entry_points.txt
sqlmakeuper-0.1.4.dist-info/top_level.txt
sqlmakeuper-0.1.4.dist-info/RECORD
