Metadata-Version: 2.1
Name: sqlmakeuper
Version: 0.1.4
Summary: SQL Formatter based on sqlparse
Home-page: https://github.com/slavadubrov/sqlformatter
Author: Viacheslav Dubrov
Author-email: slavadubrov@gmail.com
License: UNKNOWN
Platform: UNKNOWN
Classifier: Programming Language :: Python :: 3
Requires-Python: >=3.6
License-File: LICENSE
Requires-Dist: sqlparse (==0.4.2)
